{
  "title": "Адрария Вандасия",
  "Раса": "Имперец",
  "Фракция": "Сейда Нин, Канцелярия Налогов и Сборов",
  "Локация": "Сейда Нин, Склад Имперской канцелярии",
  "Квест": "Награда за голову Вандасии",
  "Услуги": "Обучение навыкам: Красноречие (55)Лёгкие доспехи (50)Скрытность (45)",
  "Состояние": null,
  "categories": [
    "Персонажи",
    "Morrowind",
    "Женщины",
    "Имперцы",
    "Сейда Нин",
    "Персонажи (Сейда Нин)",
    "Канцелярия Налогов и Сборов"
  ],
  "text": "Адрария Вандасия (ориг. Adraria Vandacia) — персонаж в игре The Elder Scrolls III: Morrowind.\n Адрария Вандасия — имперка-шпион, служит в ранге «Мытарь» в Имперской Канцелярии Налогов и Сборов. Она находится на втором этаже склада Имперской канцелярии, что в Сейда Нин. Рядом с ней почти постоянно находится имперский стражник.\n Чем-то не угодила Камонна Тонг, из-за чего попала в заказ на убийство от Лорбумола гро-Аглака, выдаваемый по соответствующему квесту Гильдии бойцов. Перциус Мерциус посоветует не убив"
}