{
  "title": "Албан Коринис",
  "Раса": "Имперец",
  "Фракция": "Нереализованные персонажи",
  "Локация": "ToddTestCrazy, дом Тодда, Пустоши",
  "Квест": null,
  "Услуги": null,
  "Состояние": null,
  "categories": [
    "Персонажи",
    "Oblivion",
    "Мужчины",
    "Имперцы",
    "Нереализованные персонажи"
  ],
  "text": "Албан Коринис (ориг. Alban Corinis) — персонаж в игре The Elder Scrolls IV: Oblivion.\n Албан Коринис — имперец-рыцарь. Присутствует сразу в 5 версиях: в комнате ToddTestCrazy, в доме Тодда и 3 версии в Пустошах. Во все эти локации можно попасть только при помощи консоли.\n Все версии носят полный эльфийский доспех, но у двух версий в Пустошах (слева и в центре) нет щита. Все версии, кроме центральной в Пустошах, вооружены эльфийским длинным мечом. Центральная версия вооружена стальным боевым молотом.\n Албан "
}