{
  "title": "Брон Тёмный Молот",
  "Раса": "Норд",
  "Фракция": "Камень Шора, Соратники, духи",
  "Локация": "Шахта Камня Шора",
  "Квест": "Выкопанные",
  "Услуги": null,
  "Состояние": null,
  "categories": [
    "Персонажи",
    "Online",
    "Мужчины",
    "Норды",
    "Камень Шора",
    "Персонажи (Камень Шора)",
    "Соратники",
    "Духи"
  ],
  "text": "В данной статье используется неофициальный вариант перевода. Если вы видите это предупреждение, пожалуйста, ознакомьтесь с инструкцией, замените текст на соответствующий официальной локализации и уберите данный шаблон.\n Брон Тёмный Молот (ориг. Bron Darkhammer) — персонаж в игре The Elder Scrolls Online.\n Долгие годы охраняли мы эту гробницу, лелея останки злобного Синмура. Войди же, чемпион!— Дух Брона Брон Тёмный Молот — дух одного из Пяти сотен Соратников Исграмора, участвовавших вместе с ним в завоевани"
}