{
  "title": "Вархильда",
  "Раса": "Норд",
  "Фракция": "Неиссякаемая фляга",
  "Локация": "Неиссякаемая фляга",
  "Квест": null,
  "Услуги": null,
  "Состояние": null,
  "categories": [
    "Персонажи",
    "Online",
    "Женщины",
    "Норды",
    "Неиссякаемая фляга"
  ],
  "text": "В данной статье используется неофициальный вариант перевода. Если вы видите это предупреждение, пожалуйста, ознакомьтесь с инструкцией, замените текст на соответствующий официальной локализации и уберите данный шаблон.\n Вархильда (ориг. Varhilda) — персонаж в игре The Elder Scrolls Online.\n Вархильда — нордка, в числе прочих отведавшая особый мёд тана Фелрига и таким образом попавшая в западню «Неиссякаемой фляги». Во время своего первого визита в таверну Бездушный увидит её у правой стены заведения, где он"
}