{
  "title": "Гвинитор",
  "Раса": "Босмер",
  "Фракция": null,
  "Локация": "Точки случайных встреч в Мрачных Трясинах",
  "Квест": null,
  "Услуги": null,
  "Состояние": null,
  "categories": [
    "Персонажи",
    "Murkmire",
    "Мужчины",
    "Босмеры"
  ],
  "text": "Гвинитор (ориг. Gwinithor) — персонаж в дополнении The Elder Scrolls Online: Murkmire.\n Ничего не понимаю! Зачем в этой игре столько правил? И как вы их запоминаете?— Гвинитор Гвинитор — босмер, мечтающий разобраться в популярной среди аргониан игре тиба-хацей. Бездушный может встретить его в одной из точек случайных встреч Мрачных Трясин. В момент встречи двое местных саксхлил, Чакка-Джи и Дж'рам-Хей, будут пытаться объяснить босмеру хотя бы общие правила игры:\n \n Бездушный может подойти поближе и заговори"
}