{
  "title": "Главарь Босек",
  "Раса": "Редгард",
  "Фракция": "Порт-Хандинг, Кровавые Кулаки",
  "Локация": "Порт-Хандинг, дворец главаря Босека",
  "Квест": "Кончик «Острия»",
  "Услуги": null,
  "Состояние": null,
  "categories": [
    "Персонажи",
    "Online",
    "Мужчины",
    "Редгарды",
    "Порт-Хандинг",
    "Персонажи (Порт-Хандинг)",
    "Кровавые Кулаки"
  ],
  "text": "Главарь Босек (ориг. Headman Bhosek) — персонаж в игре The Elder Scrolls Online.\n Главарь Босек — редгард, жестокий и коррумпированный правитель острова Строс М'Кая, проживающий в собственном дворце в Порт-Хандинге. На острове, являющемся домом для пиратов и прочего отребья, его власть зиждется на банде воинов Кровавые Кулаки. Впрочем, Босек контролирует только северную часть острова. На юге, в Порте Святых, безраздельно правят пираты капитана Эланы, именующие себя Морскими Драконами, которые кажутся многим"
}