{
  "title": "Гулмон Телас",
  "Раса": "Данмер",
  "Фракция": "Белкарт, торговцы, разные товары",
  "Локация": "Белкарт, Праздничная площадка в Белкарте",
  "Квест": null,
  "Услуги": "Торговля",
  "Состояние": null,
  "categories": [
    "События",
    "Персонажи",
    "Online",
    "Мужчины",
    "Данмеры",
    "Белкарт",
    "Торговцы",
    "Разные товары"
  ],
  "text": "\n Гулмон Телас (ориг. Gulmon Telas) — персонаж в игре The Elder Scrolls Online.\n Гулмон Телас — данмер-торговец, которого можно найти на территории праздничной площадки в Белкарте во время события Почитание Зенитара. Тёмный эльф продаёт предметы общего назначения и его ассортимент является стандартным для торговцев Краглорна: ремонтные наборы, отмычки, пустые камни душ, обычная наживка, уровневые зелья. За соответствующую плату данмер починит броню протагониста. В продаже у него также будет зацепка для нахо"
}