{
  "title": "Джарина",
  "Раса": "Редгард",
  "Фракция": "Торговый пост Рыжий Мех, кузнецы-оружейники",
  "Локация": "Гильдия бойцов, Торговый пост Рыжий Мех",
  "Квест": null,
  "Услуги": "Торговля (кузнец-оружейник)",
  "Состояние": null,
  "categories": [
    "Персонажи",
    "Online",
    "Женщины",
    "Редгарды",
    "Торговый пост Рыжий Мех",
    "Кузнецы-оружейники"
  ],
  "text": "Джарина (ориг. Jarina) — персонаж в игре The Elder Scrolls Online.\n Джарина — редгардка, член Гильдии бойцов. Её можно встретить в местном отделении Гильдии в торговом посту Рыжий Мех, что в Гратвуде, Валенвуд. Джарина является кузнецом-оружейником и оказывает услуги в сфере торговли, связанной с тяжёлыми доспехами и оружием.\n"
}