{
  "title": "Йена Кола",
  "Раса": "Имперец",
  "Фракция": "Чейдинхол",
  "Локация": "Чейдинхол",
  "Квест": "Трофеи войны",
  "Услуги": null,
  "Состояние": null,
  "categories": [
    "Персонажи",
    "Online",
    "Женщины",
    "Имперцы",
    "Чейдинхол",
    "Персонажи (Чейдинхол)"
  ],
  "text": "В данной статье используется неофициальный вариант перевода. Если вы видите это предупреждение, пожалуйста, ознакомьтесь с инструкцией, замените текст на соответствующий официальной локализации и уберите данный шаблон.\n Джена Колус (ориг. Jena Colus) — персонаж в игре The Elder Scrolls Online.\n Джена Колус — имперка, бежавшая из Имперского города из-за нежелания возвращать долг некоему Марцеллусу. Кредитор узнал её местонахождение и отправил посыльного, чтобы тот передал Джене последнее предупреждение, но п"
}