{
  "title": "Кану-са",
  "Раса": "Каджит",
  "Фракция": "Крепость Каменного Зуба",
  "Локация": "Крепость Каменного Зуба, Бетник",
  "Квест": null,
  "Услуги": null,
  "Состояние": null,
  "categories": [
    "Персонажи",
    "Online",
    "Мужчины",
    "Каджиты",
    "Крепость Каменного Зуба",
    "Персонажи (Крепость Каменного зуба)"
  ],
  "text": "Кану-са (ориг. Kanoo-sa) — персонаж в игре The Elder Scrolls Online.\n Кану-са — каджит-кузнец, проживающий в крепости Каменного Зуба на острове Бетник. Он находится в доках, где спит в одной из пришвартованных лодок. Полноценный диалог с ним невозможен.\n"
}