{
  "title": "Киил-Раниур",
  "Раса": "Аргонианин",
  "Фракция": "Кальдера",
  "Локация": "Кальдера",
  "Квест": null,
  "Услуги": null,
  "Состояние": null,
  "categories": [
    "Персонажи",
    "Morrowind",
    "Женщины",
    "Аргониане",
    "Кальдера",
    "Персонажи (Кальдера)"
  ],
  "text": "Киил-Раниур (ориг. Keel-Raniur) — персонаж в игре The Elder Scrolls III: Morrowind.\n Киил-Раниур — аргонианка-обыватель, которая целый день бродит по улицам Кальдеры. Владеет собственностью в поселении, но предпочитает находиться вне помещения, по-видимому, наблюдая за местными жителями. Аргонианка не связана с каким-либо заданием и не предоставляет услуг.\n Из одежды Киил-Раниур носит только простую мантию и такое же кольцо. Не вооружена. Имеет при себе уровневое количество золота, а также ключ от своего до"
}