{
  "title": "М'дирр",
  "Раса": "Каджит",
  "Фракция": "Пограничная застава",
  "Локация": "Пограничная застава, дом М'дирра",
  "Квест": "Шеогорат",
  "Услуги": null,
  "Состояние": null,
  "categories": [
    "Персонажи",
    "Oblivion",
    "Мужчины",
    "Каджиты",
    "Пограничная застава"
  ],
  "text": "М'дирр (ориг. M'dirr) — персонаж в игре The Elder Scrolls IV: Oblivion.\n М'дирр — каджит, проживающий вместе с Тсрамлой в собственном доме в Пограничной заставе. Как и все остальные жители поселения, очень суеверен и считает, что «три знака К'Шарры» означают неминуемый конец света.\n М'дирр просыпается в 4 часа утра, а затем бродит по поселению целый день, разговаривая с другими жителями. В 11 часов утра направится на двухчасовой обед в ближайшую таверну. В 10 часов вечера вернётся домой на сон. Когда пророч"
}