{
  "title": "Мальтагрос",
  "Раса": "Босмер",
  "Фракция": "Эвермор, Скупщики краденого",
  "Локация": "Эвермор, убежище преступников Эвермора",
  "Квест": null,
  "Услуги": "Торговля (Скупщик краденых товаров)",
  "Состояние": null,
  "categories": [
    "Персонажи",
    "Online",
    "Мужчины",
    "Босмеры",
    "Эвермор",
    "Персонажи (Эвермор)",
    "Скупщики краденого"
  ],
  "text": "Мальтагрос (ориг. Malthagros) — персонаж в игре The Elder Scrolls Online.\n Мальтагрос — босмер, скупающий краденые товары в убежище преступников, расположенном под столицей Бангкорая городом Эвермор. Его лавка, расположенная в северо-восточной части убежища, называется «Всё для карманника».\n В разговоре с Бездушным может произнести одну из следующих фраз:\n Если протагонист превысил дневную норму продажи украденных вещей, босмер скажет: «Я бы попробовал тебе помочь, но у меня дел по горло. Приходи попозже».\n"
}