{
  "title": "Нимари",
  "Раса": "Альтмер",
  "Фракция": "Марбрук, хозяева конюшен",
  "Локация": "Марбрук, Благородные скакуны Нимари",
  "Квест": null,
  "Услуги": "Хозяин конюшни",
  "Состояние": null,
  "categories": [
    "Персонажи",
    "Online",
    "Женщины",
    "Альтмеры",
    "Марбрук",
    "Персонажи (Марбрук)",
    "Хозяева конюшен"
  ],
  "text": "Нимаре (ориг. Nimare) — персонаж в игре The Elder Scrolls Online.\n Обычно я бы сказала, что верхом по лесу не проскачешь, но это особенные леса. Порой животные находят дорогу лучше, чем я— Нимари при разговоре Нимари — альтмерка, которую Бездушный может найти в конюшне «Благородные скакуны Нимари», что в Марбруке в регионе Гриншейд, Валенвуд. Она является хозяином конюшни и может продать герою лошадь, а также дать ему урок верховой езды, улучшив один из соответствующих навыков при наличии у протагониста езд"
}