{
  "title": "Офицер Лорин",
  "Раса": "Альтмер",
  "Фракция": "Первый Альдмерский Доминион, Талмор",
  "Локация": "Гнездо Кенарти, Плантация «Пятнистая ракушка»",
  "Квест": "Семейное дело",
  "Услуги": null,
  "Состояние": null,
  "categories": [
    "Персонажи",
    "Online",
    "Женщины",
    "Альтмеры",
    "Первый Альдмерский Доминион",
    "Талмор"
  ],
  "text": "В данной статье используется неофициальный вариант перевода. Если вы видите это предупреждение, пожалуйста, ознакомьтесь с инструкцией, замените текст на соответствующий официальной локализации и уберите данный шаблон.\n Офицер Лорин (ориг. Officer Lorin) — персонаж в игре The Elder Scrolls Online.\n Офицер Лорин — альтмерка, призванная поддерживать мир и порядок на острове Гнездо Кенарти. Найти её можно на плантации «Пятнистая ракушка», где она расследует причину произошедшего там пожара.\n"
}