{
  "title": "Пелагий Замученный",
  "Раса": "бретон",
  "Фракция": null,
  "Локация": "Ум Безумца",
  "Квест": "Безумный ум",
  "Услуги": null,
  "Состояние": null,
  "categories": [
    "Персонажи",
    "Skyrim",
    "Мужчины",
    "Бретоны"
  ],
  "text": "Пелагий Замученный (ориг. Pelagius the Tormented) — персонаж в игре The Elder Scrolls V: Skyrim.\n Является одним из аспектов разрушенного рассудка мёртвого двенадцатого императора Империи Септимов, Пелагия III, известного так же, как Пелагий Безумный.\n В ходе задания Принца Даэдра Шеогората «Безумный ум» Довакин попадает в странное место — Ум Безумца — физическое воплощение разума Пелагия III.\n Чтобы выбраться отсюда ему, с помощью даэдрического артефакта, посоха Ваббаджек нужно исцелить три основных патоло"
}