{
  "title": "Ребекка Лирлейн",
  "Раса": "Бретон",
  "Фракция": "Чёрные Надзиратели",
  "Локация": "Руины Чид-Моска",
  "Квест": null,
  "Услуги": null,
  "Состояние": null,
  "categories": [
    "Чёрные Надзиратели",
    "Online",
    "Персонажи",
    "Женщины",
    "Бретоны",
    "Боссы"
  ],
  "text": "Ребекка Лирлейн (ориг. Rebecca Lirlane) —  босс в игре The Elder Scrolls Online.\n У нас гости! Защищайте кошмарный идол!— Ребекка Лирлейн Ребекка Лирлейн — бретонка, член преступной группировки Чёрные Надзиратели, по приказу Марга Дерия обыскивавших руины Чид-Моска в поисках особого кошмарного идола, содержащего в себе сведения о местонахождении запретного острова Норг-Тзел. Идол был найден, и хранившаяся внутри ксилография была извлечена, но немалая часть Чёрных Надзирателей, в том числе и Ребекка, осталис"
}