{
  "title": "Скульвар Чёрная Рукоять",
  "Раса": "Норд",
  "Фракция": "Вайтран, торговцы",
  "Локация": "Вайтран — Конюшни",
  "Квест": null,
  "Услуги": "Продажа лошадей",
  "Состояние": null,
  "categories": [
    "Персонажи",
    "Skyrim",
    "Мужчины",
    "Норды",
    "Вайтран",
    "Персонажи (Вайтран)",
    "Торговцы"
  ],
  "text": "Скульвар Черная Рукоять (ориг. Skulvar Sable-Hilt) — персонаж в игре The Elder Scrolls V: Skyrim.\n Скульвар Чёрная Рукоять — норд, владелец конюшни и фермер в Вайтране. Может продать за 1000 септимов лошадь по кличке Королева Альфсигра (или просто Алли). Считает, что его сын недостаточно умён, чтобы быть хозяином конюшни. Однако, после смерти Скульвара Йервар прекрасно его заменяет. \n Скульвар — возможная цель различных Radiant-квестов.\n"
}