{
  "title": "Судоводитель",
  "Раса": "Данмер",
  "Фракция": "Морнхолд, лодочники, нежить, духи",
  "Локация": "Морнхолд, Шад Астула",
  "Квест": null,
  "Услуги": null,
  "Состояние": null,
  "categories": [
    "Персонажи",
    "Online",
    "Мужчины",
    "Данмеры",
    "Морнхолд",
    "Персонажи (Морнхолд)",
    "Лодочники",
    "Нежить",
    "Духи"
  ],
  "text": "В данной статье используется неофициальный вариант перевода. Если вы видите это предупреждение, пожалуйста, ознакомьтесь с инструкцией, замените текст на соответствующий официальной локализации и уберите данный шаблон.\n Судоводитель (ориг. The Boatmaster) — персонаж в игре The Elder Scrolls Online.\n Судоводитель — дух данмера, которого можно найти в Морнхолде. Протагонист должен убедить духа перенести его в школу магии под названием Шад Астула.\n"
}