{
  "title": "Урог",
  "Раса": "Орк",
  "Фракция": "Нарзулбур, племена орков",
  "Локация": "Нарзулбур",
  "Квест": null,
  "Услуги": null,
  "Состояние": null,
  "categories": [
    "Персонажи",
    "Skyrim",
    "Женщины",
    "Орки",
    "Нарзулбур",
    "Племена орков"
  ],
  "text": "Урог (ориг. Urog) — персонаж в игре The Elder Scrolls V: Skyrim.\n Урог — девушка-орк. Она является дочерью вождя Махулака и сестрой Душнамуба. Урог хочет стать сильным охотником, и поэтому занимается тренировкой с манекеном с 7 утра до 7 вечера возле Длинного дома Махулака. После тренировок Урог возвращается домой, ужинает до полуночи и ложится спать.\n Урог носит меховую броню и пару сапог изгоев. Носит при себе орочий лук и боевой топор.\n"
}