{
  "title": "Фалиса аф-Армин",
  "Раса": "Редгард",
  "Фракция": "Сентинель",
  "Локация": "Сентинель, трактир «Сёстры песков»",
  "Квест": "Поиски закончены",
  "Услуги": null,
  "Состояние": null,
  "categories": [
    "Персонажи",
    "Online",
    "Женщины",
    "Редгарды",
    "Сентинель",
    "Персонажи (Сентинель)"
  ],
  "text": "Фалиса аф-Армин (ориг. Falisa af-Armin) — персонаж в игре The Elder Scrolls Online.\n Фалиса аф-Армин — редгардка, приживающая в городе Сентинель. Семь лет назад её муж отправился на поиски могилы своего далёкого предка, Сабасада Щита, и до сих пор не вернулся. Полагая, что он уже давно сгинул в песках Алик'ра, Фалиса теперь всё своё время проводит с книгой в руках в местной таверне «Сёстры песков». Если заговорить с редгардкой, она лишь скажет: «Не видно, что я тут читать пытаюсь? Оставь меня в покое, пожал"
}