{
  "title": "Элисон Жюрар",
  "Раса": "Бретон",
  "Фракция": "Шорнхельм, зачарователи",
  "Локация": "Чары «Свечение камня», Шорнхельм",
  "Квест": null,
  "Услуги": "Торговля (зачарователь)",
  "Состояние": null,
  "categories": [
    "Персонажи",
    "Online",
    "Женщины",
    "Бретоны",
    "Шорнхельм",
    "Персонажи (Шорнхельм)",
    "Зачарователи"
  ],
  "text": "В данной статье используется неофициальный вариант перевода. Если вы видите это предупреждение, пожалуйста, ознакомьтесь с инструкцией, замените текст на соответствующий официальной локализации и уберите данный шаблон.\n Элисон Жюрар (ориг. Alison Jurard) — персонаж в игре The Elder Scrolls Online.\n Да, я самый выдающийся зачарователь в Шорнхельме. Если тебе нужно что-то зачаровать, возможно, я смогу тебе помочь. Не стесняйся, можешь осмотреть мой ассортимент— Элисон Жюрар Элисон Жюрар — бретонка, живущая в "
}