{
  "title": "Эрвер Дивейн",
  "Раса": "Данмер",
  "Фракция": "Деменция, Дипваллоу",
  "Локация": "Дипваллоу, Дом Эрвера Дивейна",
  "Квест": "Призраки Холма Самоубийств",
  "Услуги": null,
  "Состояние": null,
  "categories": [
    "Персонажи",
    "Shivering Isles",
    "Персонажи (Shivering Isles)",
    "Мужчины",
    "Мужчины (Shivering Isles)",
    "Данмеры",
    "Данмеры (Shivering Isles)",
    "Деменция",
    "Дипваллоу"
  ],
  "text": "Эрвер Дивейн (ориг. Erver Devani) — персонаж в дополнении The Elder Scrolls IV: Shivering Isles.\n Ты! Ты… ты не из них. Но тебе всё равно нечего здесь делать. И если их увидишь, скажи, что Эрвер готов и всегда начеку— Эрвер при приветствии Эрвер Дивейн — данмер, живущий в деревне Дипваллоу. Он ужасно боится внешнего мира и «Их». Живёт достаточно изолированно. Эрвер безумен. Его преследует страх Их, поэтому он постоянно сидит дома. Он является единственным жителем Островов, который может рассказать о призрак"
}