{
  "title": "Валандрус Абор",
  "Раса": "Имперец",
  "Фракция": "Скинград, Служители Девяти",
  "Локация": "Скинград, Великая часовня Джулианоса",
  "Квест": null,
  "Услуги": null,
  "Состояние": null,
  "categories": "Персонажи, Oblivion, Мужчины, Имперцы, Скинград, Персонажи (Скинград), Служители Девяти",
  "text": "Валандрус Абор (ориг. Valandrus Abor) — персонаж в игре The Elder Scrolls IV: Oblivion.\n Я Валандрус Абор, примас Джулианоса. Можешь обращаться ко мне „ваше преосвященство“— Валандрус Абор Валандрус Абор — примас Великой часовни Джулианоса в Скинграде. Несмотря на свой высокий сан, очень высокомерный и неприятный человек. Отношение жителей Скинграда к этому напыщенному имперцу становится ясным с первых же слов:\n И если общение с Туминдилом и Мари Палиэлль для героя будет очень приятным, Валандрус Абор оставит о себе очень нехорошее впечатление: «Я Валандрус Абор, примас Джулианоса. Можешь обращаться ко мне „ваше преосвященство“». Будучи столь уверенным в своём превосходстве над другими, он даже не захочет ничего рассказать о городе, в котором живёт. Более того, он даже оскорбит собеседника, что совершенно не вяжется с его саном: «У примаса есть дела поважнее, чем предоставлять информацию для любопытных. У нищих много свободного времени. Уверен, у тебя с ними много общего».\n Естественно, Валандрус ничему не учит и не предоставляет никаких услуг. Но в бою, как и любой целитель, он пользуется уровневым набором заклинаний, плюс дополнительно ещё одним высокоуровневым заклинанием школы «Восстановление».\n Он спит в своей постели в холле часовни с полуночи до 6 утра, а затем прохаживается по главному помещению часовни до полудня. Затем он тратит два часа на прогулку по Скинграду, прежде чем отправиться обратно в часовню в 2 часа дня и провести там оставшееся до полуночи время.\n Валандрус Абор одет в синий бархатный наряд и синие замшевые туфли. В его карманах можно найти только несколько золотых монет.\n"
}