{
  "title": "Гундинг",
  "Раса": "Норд",
  "Фракция": "Шахтёры",
  "Локация": "Свистящая шахта",
  "Квест": null,
  "Услуги": null,
  "Состояние": null,
  "categories": "Персонажи, Skyrim, Мужчины, Норды, Шахтёры",
  "text": "Гундинг (ориг. Gunding) — персонаж в игре The Elder Scrolls V: Skyrim.\n Гундинг — норд, работает шахтёром в Свистящей шахте. Он пытается убедить себя, что шахта может принести прибыль.\n Гундинг спит на одном из спальников с 8 вечера до 8 утра. Когда он не спит, он бродит вокруг шахты, добывает руду из жил или заниматься приготовлением пищи.\n Гундинг носит шахтёрскую одежду и пару сапог. Вооружён железным боевым топором.\n"
}