{
  "title": "Джастия Синтав",
  "Раса": "Имперец",
  "Фракция": "Имперский город",
  "Локация": "Имперский город, Эльфийские сады",
  "Квест": null,
  "Услуги": null,
  "Состояние": null,
  "categories": "Персонажи, Oblivion, Женщины, Имперцы, Имперский город, Персонажи (Имперский город)",
  "text": "Джастия Синтав (ориг. Jastia Sintav) — персонаж в игре The Elder Scrolls IV: Oblivion.\n Джастия Синтав — имперка, живущая вместе с сестрой Дженой в Эльфийских садах Имперского города. Принадлежит к семье Синтав — одному из самых уважаемых кланов в Имперском городе. Её можно встретить блуждающей в своём районе или ухаживающей за своим дядей Иниэлем. Как и все Синтавы, враждует с кланом Атиусов.\n Одета в одежду среднего класса: стёганый дублет, коричневую одежду и туфли из оленьей кожи. Носит с собой ключ от дома, а также уровневое количество золота.\n"
}