{
  "title": "Джавид",
  "Раса": "Редгард",
  "Фракция": "Эпплвотч, музыканты",
  "Локация": "Трактир «Эпплвотч»",
  "Квест": null,
  "Услуги": null,
  "Состояние": null,
  "categories": "Персонажи, Online, Мужчины, Редгарды, Эпплвотч, Музыканты",
  "text": "Джавид (ориг. Javid) — персонаж в игре The Elder Scrolls Online.\n В Алик'ре я выступал перед королевскими особами. А здесь…Согласился выступать за долю от доходов таверны. Ловко же этот пройдоха Леон меня одурачил!— Джавид Джавид — редгардский бард, которого владелец трактира «Эпплвотч» Леон Драконис убедил перебраться из Алик'р в своё заведение, расположенное на севере Сиродила, пообещав в обмен на выступления отдавать часть дохода таверны. Вторжение даэдра и война привела к тому, что дороги региона обезлюдели, а засевшая поблизости шайка разбойников из банды «Чёрные Кинжалы» лишила это место последних возможных посетителей, в результате чего Джавид остался с пустыми карманами.\n"
}