{
  "title": "Древесная целительница Ксоханил",
  "Раса": "Аргонианин",
  "Фракция": "Хадж Уксит, древесные целители",
  "Локация": "Хадж Уксит, Пустой город",
  "Квест": "Мудрость веков",
  "Услуги": null,
  "Состояние": null,
  "categories": "Персонажи, Online, Женщины, Аргониане, Хадж Уксит, Древесные целители",
  "text": "В данной статье используется неофициальный вариант перевода. Если вы видите это предупреждение, пожалуйста, ознакомьтесь с инструкцией, замените текст на соответствующий официальной локализации и уберите данный шаблон.\n Древесная целительница Ксоханил (ориг. Treeminder Xohaneel) — персонаж в игре The Elder Scrolls Online.\n Древесная целительница Ксоханил — аргонианка, проживающая в поселении Хадж Уксит, что в Хладной Гавани. Она является лидером одной из двух фракций, на которые разделилось общество городка. Будучи учёной, Ксоханиль отстаивает мнение половины жителей, а именно: дерево хист должно умереть. Ей противостоит Ан-Джин-Сакка, который вместе с воинами является сторонником сохранения дерева.\n Бездушный, прибывший в Хадж Уксит в ходе своих странствий, встречается с аргонианкой на окраине поселения. Позже на площадке перед деревом хист, где возникает очередной спор, она попросит героя помочь. Ан-Джин-Сакка не хочет посвящать незнакомца в дела поселения, покуда тот не пройдёт испытание Духа и Тела. Древесная целительница Ксоханиль выдаст задание на испытание Духа. После его успешного прохождения герой предстанет перед выбором, от которого зависит будущее Хадж Уксита. После окончания событий в городке она вместе с другими аргонианами переберётся в Пустой город.\n"
}