{
  "title": "Дракон Щитов",
  "Раса": "Имперец",
  "Фракция": "Драконья Стража",
  "Локация": "База Альдмерского Доминиона, база Даггерфолльского Ковенанта, база Эбонхартского Пакта",
  "Квест": null,
  "Услуги": null,
  "Состояние": null,
  "categories": "Персонажи, Imperial City, Персонажи (Imperial City), Мужчины, Мужчины (Imperial City), Имперцы, Имперцы (Imperial City), Драконья Стража",
  "text": "Дракон Щитов (ориг. The Drake of Shields) — персонаж в дополнении The Elder Scrolls Online: Imperial City.\n Дракон Щитов — имперец, служивший в Драконьей Страже. Дракон Щитов появляется на базе альянса после выполнения квеста «Великая жаровня»:\n "
}