{
  "title": "Жосслин Сидрей",
  "Раса": "Бретон",
  "Фракция": "Культ Червя, некроманты, мёртвые персонажи",
  "Локация": "На тропе, ведущей к Форелхосту",
  "Квест": null,
  "Услуги": null,
  "Состояние": null,
  "categories": "Персонажи, Online, Женщины, Бретоны, Культ Червя, Некроманты, Мёртвые персонажи",
  "text": "Жосслин Сидрей (ориг. Josseline Sidrey) — персонаж в игре The Elder Scrolls Online.\n Жосслин Сидрей — бретонка, которую можно найти мёртвой на пути, ведущем к вершине горы Форелхост. Жосслин была членом культа Червя и частью группы некромантов под предводительством Нордаля, завладевших обломком Вутрад и решивших заодно ещё и ограбить гробницу драконьего жреца в надежде заполучить одну из легендарных масок. Но культисты недооценили это место. Сперва убийственный холод, а затем невозможность открыть двери в саму гробницу и пробудившиеся драугры заставили их бежать, оставив наверху тело своего предводителя. На обратном пути их атаковали саблезубы и вряд ли кому из культистов удалось уйти с горы живым. Среди погибших была и Жосслин, чьё тело Бездушный найдёт в нижней части склона. При себе у неё будет письмо к сестре, в котором Жосслин весьма нелестно отзывается о вожаке своей группы.\n"
}