{
  "title": "Идог",
  "Раса": "Норд",
  "Фракция": "Шиммерин, Гильдия бойцов",
  "Локация": "Гильдия бойцов, Шиммерин",
  "Квест": null,
  "Услуги": null,
  "Состояние": null,
  "categories": "Персонажи, Summerset, Мужчины, Норды, Шиммерин, Гильдия бойцов",
  "text": "Идог (ориг. Idaug) — персонаж в главе The Elder Scrolls Online: Summerset.\n Избегай встречи со служителями Божественного Надзора, если можешь. Они не то чтобы недружелюбны, но, похоже, предпочитают, чтобы к ним не лезли— Идог Идог — норд, проживающий в Шиммерине, что в регионе Саммерсет. Найти его можно в местном отделении Гильдии бойцов. Всё своё время проводит, бродя по зданию.\n При приветствии произносит одну из следующих фраз:\n"
}