{
  "title": "Иллио",
  "Раса": null,
  "Фракция": null,
  "Локация": null,
  "Квест": null,
  "Услуги": null,
  "Состояние": null,
  "categories": "Lore, Альдмеры, Мужчины, Персонажи",
  "text": "Иллио (ориг. Illio) (? — ?) — альдмерский исследователь.\n …Второй корабль „Пасквиниель“, управляемый рулевым Иллио, должен был следовать по путеводному Камню юга…— Из книги «Отец Нибена» Иллио — альдмерский исследователь, капитан корабля «Пасквиниель». Он должен был плыть на юг, чтобы исследовать окрестные земли и попытаться найти путь в Альдмерис. Он не вернулся из этого путешествия, и можно предположить, что Иллио доплыл до Пиандонеи и попал в руки маормеров.\n"
}