{
  "title": "Клеса",
  "Раса": "Редгард",
  "Фракция": "Анвил",
  "Локация": "Анвил, конюшня «Спокойные лошади»",
  "Квест": null,
  "Услуги": "Продажа лошадей",
  "Состояние": null,
  "categories": "Персонажи, Oblivion, Женщины, Редгарды, Анвил, Персонажи (Анвил)",
  "text": "Клеса (ориг. Clesa) — персонаж в игре The Elder Scrolls IV: Oblivion.\n Я Клеса. Мой муж и я содержим лошадей, лучших в Анвиле— Клеса при знакомстве Клеса — редгардка, владелица конюшни «Спокойные лошади». Продаёт белых лошадей. Замужем за Эрнестом, однако при этом находится в неведении относительно его похождений на́ сторону.\n Клеса носит коричневую рубашку, светло-коричневую одежду и грубые кожаные туфли. Вооружена коротким железным мечом. Имеет уровневое количество золота.\n В то время как её муж Эрнест без всякого энтузиазма ухаживает за лошадьми и заманивает потенциальных клиентов, сама Клеса управляет финансовой стороной дел, не покидая при этом конюшен. Каждый день она просыпается в 6 утра и бесцельно блуждает по комнате два часа, прежде чем отпереть дверь в 8 утра. В течение следующих 12-ти часов «Спокойные лошади» будут открыты, а Клеса будет готова принять любого клиента даже в перерыв на обед, на который у неё выделен промежуток с полудня до 2-ух часов дня. В 6 вечера она снова садится за стол и ужинает до 8-ми вечера, после чего закрывается на ночь. После того, как конюшни окажутся заперты, Клеса отдыхает пару часов, пока наконец не ложится спать в 10 вечера.\n Клеса продаёт лошадей круглые сутки, но сама конюшня закрывается на ночь.\n"
}