{
  "title": "Маринора",
  "Раса": "Босмер",
  "Фракция": "Первый Альдмерский Доминион, Орлиное Взморье",
  "Локация": "Орлиное Взморье",
  "Квест": null,
  "Услуги": null,
  "Состояние": null,
  "categories": "Персонажи, Online, Женщины, Босмеры, Первый Альдмерский Доминион, Орлиное Взморье, Персонажи (Орлиное Взморье)",
  "text": "Маринора (ориг. Marinora) — персонаж в игре The Elder Scrolls Online.\n Маринора — босмерка, солдат Альдмерского Доминиона, находившаяся на борту одного из кораблей флотилии, уничтоженной призванной маормерами бурей у берегов Гнезда Кенарти. Теперь она целый день с зажжённым факелом бродить по лагерю, который выжившие разбили в старых руинах Орлиное Взморье, что на юге острова. Уникальных диалогов босмерка не имеет, при попытке заговорить будет отвечать стандартными фразами.\n\n"
}