{
  "title": "Провентус Авениччи",
  "Раса": "Имперец",
  "Фракция": "Вайтран, управители",
  "Локация": "Вайтран, Драконий Предел",
  "Квест": null,
  "Услуги": "Продаст в Вайтране дом и обустроит его за отдельную плату.",
  "Состояние": null,
  "categories": "Персонажи, Skyrim, Мужчины, Имперцы, Вайтран, Персонажи (Вайтран), Управители",
  "text": "Провентус Авениччи (ориг. Proventus Avenicci) — персонаж в игре The Elder Scrolls V: Skyrim.\n Провентус Авениччи — имперец, управитель ярла Балгруфа Старшего. Сторонник Империи, считающий традиции нордов дремучим варварством. Это особенно заметно по его комментариям о призыве Седобородыми Довакина. Если в гражданской войне победят Братья Бури, переедет в Солитьюд.\n Найти его всегда можно в Драконьем Пределе. Обычно он стоит рядом с троном ярла, но иногда находится в военной комнате за тронным залом, на галерее или в своей спальне в покоях ярла.\n Он предоставляет информацию о Вайтране, а также выдаёт Radiant-квесты — убить лидера бандитов или великана (награда 100 золотых). Если герой станет таном Вайтрана, у Провентуса можно будет купить Дом тёплых ветров в Вайтране за 5000 септимов и детали интерьера.\n Можно стать свидетелем разговора Провентуса с Хронгаром, братом  ярла Балгруфа. Хронгар будет просить Провентуса о том, чтобы он помог склонить Балгруфа на сторону Империи и помочь им победить в Гражданской войне.\n"
}