{
  "title": "Рерлас Мон",
  "Раса": "Бретон",
  "Фракция": null,
  "Локация": "Морнхолд, Великий Базар",
  "Квест": null,
  "Услуги": "Торговец-дрессировщик",
  "Состояние": null,
  "categories": "Персонажи, Tribunal, Мужчины, Бретоны",
  "text": "Рерлас Мон (ориг. Rerlas Mon) — персонаж в дополнении The Elder Scrolls III: Tribunal.\n Рерлас Мон — дрессировщик-бретон, которого можно встретить на Великом Базаре среди торговых лавок. Он торгует обученными скрибами и крысами. Среди последних есть вьючные, способные перевозить на себе грузы (их грузоподъемность равна 100). Эти животные будут следовать за главным героем и нападать на агрессивных существ. Скрибы полезны ещё и тем, что способны парализовать врага своим ядом. Правда, эти животные довольно слабы, поэтому не подходят в качестве помощников для убийства даже самых слабых существ из дополнения The Elder Scrolls III: Tribunal, не говоря уже о Саласе Валоре или Гаэноре. Единственная их возможная польза — на время отвлечь противника в бою.\n Когда протагонист покупает животных у бретона, в его дневнике появляется запись о покупке. Расценки на тренированных животных следующие:\n Продав по три особи, Рерласу понадобится некоторое время, чтобы выдрессировать новых. Всего он может продать до шести каждого типа. Стоит беречь питомцев: если умрут все шесть, Рерлас обидится на такое обращение и откажется разговаривать.\n Как и все бретоны, Рерлас имеет сопротивление магии, может повышать магию и создать магический щит.\n Обученные животные"
}