{
  "title": "Саден",
  "Раса": "Данмер",
  "Фракция": "Кровавые хоркеры, мёртвые персонажи",
  "Локация": "Остров Хоркеров",
  "Квест": null,
  "Услуги": null,
  "Состояние": null,
  "categories": "Персонажи, Dragonborn, Мужчины, Данмеры, Кровавые хоркеры, Мёртвые персонажи, Пираты",
  "text": "Саден (ориг. Saden) — персонаж в дополнении The Elder Scrolls V: Dragonborn.\n Мы высунулись и посмотрели за камни, я даже не могу описать, что мы увидели, хотя никогда этого не забуду. Кровь. Боги, сколько крови…— Дневник Садена Саден — покойный данмер, тело которого можно найти на холме острова Хоркеров. По его дневнику ясно, что он был частью пиратской группы, которые позднее назвали себя «Кровавые хоркеры».\n"
}