{
  "title": "Тундулсавен",
  "Раса": "Альтмер",
  "Фракция": "Порт-Хандинг",
  "Локация": "Порт-Хандинг, Дворец главаря Босека",
  "Квест": null,
  "Услуги": null,
  "Состояние": null,
  "categories": "Персонажи, Online, Женщины, Альтмеры, Порт-Хандинг, Персонажи (Порт-Хандинг)",
  "text": "Тундулсавен (ориг. Tundulsawen) — персонаж в игре The Elder Scrolls Online.\n Тундулсавен — альтмерка-рабыня, служанка во дворце главаря Босека в Порт-Хандинге на острове Строс М'Кай. Находится на первом этаже башни в восточной части дворца. Всё своё время сидит в кресле с кружкой в руках. Полноценный диалог с ней невозможен, при попытке заговорить будет отвечать общими фразами.\n"
}