{
  "title": "Фарусея Салас",
  "Раса": "Данмер",
  "Фракция": "Пелагиад",
  "Локация": "Пелагиад",
  "Квест": null,
  "Услуги": null,
  "Состояние": null,
  "categories": "Персонажи, Morrowind, Женщины, Данмеры, Пелагиад, Персонажи (Пелагиад)",
  "text": "Фарусея Салас (ориг. Farusea Salas) — персонаж в игре The Elder Scrolls III: Morrowind.\n Фарусея Салас — данмерка-обыватель, бродит неподалёку от своего дома в северо-западной части Пелагиада, между жилищами Ли-Лея и Мадреса Навура. Она не выдаёт никаких квестов и не предоставляет каких-либо услуг. Единственная польза от неё — наводки на Нелоса Онмара и Игфу в ходе квестов «Красотка и бандит» и «Cеребряный кубок» соответственно.\n Фарусея носит простую одежду: ботинки, рубашку и юбку. Не вооружена. Золота нет.\n Наиболее развитые навыки Фарусеи:\n Помимо расовых данмерских, никакими талантами и заклинаниями не обладает.\n"
}