{
  "title": "Фаулерот",
  "Раса": "Босмер",
  "Фракция": "Ворота Валенвуда",
  "Локация": "Ворота Валенвуда",
  "Квест": null,
  "Услуги": null,
  "Состояние": null,
  "categories": "Персонажи, Elsweyr, Мужчины, Босмеры, Ворота Валенвуда",
  "text": "Фаулерот (ориг. Fauleroth) — персонаж в главе The Elder Scrolls Online: Elsweyr.\n Фаулерот — босмер, которого можно встретить на территории торгового поста Ворота Валенвуда, находящегося на юго-западе Северного Эльсвейра, у границы с Гратвудом. Всё своё время лесной эльф проводит на одной из открытых террас этого места, попивая вино из бокала. Уникальных диалогов Фаулерот не имеет, при попытке заговорить будет отвечать стандартными фразами.\n\n"
}