{
  "title": "Хартмин",
  "Раса": "Босмер",
  "Фракция": null,
  "Локация": "Поляна у юго-западного входа в Лабиринт",
  "Квест": "Цветок юности",
  "Услуги": null,
  "Состояние": null,
  "categories": "Персонажи, Online, Мужчины, Босмеры",
  "text": "Хартмин (ориг. Hartmin) — персонаж в игре The Elder Scrolls Online.\n Хартмин — босмер, которого Бездушный встретит на юге Гриншейда, на поляне юго-западные входа в Лабиринт. Рядом с ним на траве будет лежать другой лесной эльф, Мирилир. Выясняется, что это муж Хартмина и он умирает. Супруг пришёл с ним в это место, чтобы дать ему в последний раз взглянуть на цветы улыбка нереиды, которыми они некогда так любовались в юности. Но цветов здесь больше нет и босмер попросит протагониста пройтись по округе, чтоб попытаться найти это растение и принести ему семена:\n \n Единственную улыбку нереиды главный герой находит в развалинах дома у дороги, ведущей в Гринхарт. После того, как он оберёт с цветка семена, всё помещение заполнят призрачные растения и послышатся голоса Хартмина и Мирилира:\n \n Когда Бездушный возвращается с семенами на поляну, Мирилир уже мёртв:\n \n Забрав семена из рук Бездушного, босмер рассыпает их по всей поляне: «Прощай, Мирилир. Я сею эти семена в память о нашей жизни. Даже когда нас не станет, другие придут сюда и обретут ту же радость, что обрели мы в цветах и друг в друге. И пусть наша любовь будет возрождаться… вечно». Спустя несколько мгновений по всей поляне появляются призрачные цветы улыбка нереиды. Если после этого снова заговорить с босмером, он скажет: «Ты видишь их? Видишь эти цветы? Они прелестны… просто прелестны».\n"
}