{
  "title": "Хул-Ван",
  "Раса": "Аргонианин",
  "Фракция": null,
  "Локация": "Доминус-Фатум",
  "Квест": "Ритуал изменения",
  "Услуги": null,
  "Состояние": null,
  "categories": "Персонажи, Murkmire, Женщины, Аргониане",
  "text": "Хул-Ван (ориг. Hul-Wan) — персонаж в дополнении The Elder Scrolls Online: Murkmire.\n Хул-Ван — аргонианка, которую Бездушный встретит во время сбора древесины, что крошит камень. Найти этот необходимый для ритуала вастей-сей компонент можно на севере Мрачных Трясин, у водопада рядом с навеки повисшим на ветвях дерева древним кораблём времён Алессианской империи «Доминус-Фатум». Растущий здесь баньян пророс прямо сквозь камень, именно его древесина, как объяснил Бездушному ниссво Парази, нужна для активации Зинчей-Кону. Когда протагонист подойдёт к дереву, стоящая рядом Хул-Ван скажет: «Стой, оджель! Зачем ты приближаешься к дереву, которое крошит камень?»\n Главный герой может просто собрать лежащие рядом сухие ветки, но может и немного задержаться и объяснить аргонианке, что не собирается причинять растению никакого вреда:\n \n Если заговорить с аргонианкой вновь, она будет отвечать одной фразой: «Желаю удачи с ритуалом, оджель». Если же изначально решить не разговаривать с Хул-Ван, а просто собрать сухие ветви, а уже потом заговорить, аргонианка скажет: «Доброго пути, оджель», после чего просто уйдёт.\n"
}